{
    "key": "believable veils",
    "name": "Believable Veils",
    "url": "https://www.aonprd.com/FeatDisplay.aspx?ItemName=Believable%20Veils",
    "source": ["Inner Sea Gods pg. 207"],
    "text": "The teachings of your deity help you keep your secrets safe.",
    "prerequisites": "Caster level 3rd, ability to cast at least one glamer or figment, worshiper of Sivanah.",
    "benefit": "Once per day when you create a glamer or figment effect, you can empower the effect so that the DC to disbelieve it is 2 higher than normal."
}
