{
    "key": "blood frenzy strike",
    "name": "Blood Frenzy Strike",
    "url": "https://www.aonprd.com/FeatDisplay.aspx?ItemName=Blood%20Frenzy%20Strike",
    "descriptors": ["Combat"],
    "source": ["Heroes from the Fringe pg. 31"],
    "description": "Your strikes tear at an opponent’s flesh, inflicting serious wounds, and you can unleash all of your pent-up rage in a single powerful blow.",
    "prerequisites": "Str 15, Blood Frenzy Style, Improved Unarmed Strike, Power Attack, base attack bonus +4, aquatic subtype.",
    "benefit": "While you are using Blood Frenzy Style, when you damage an opponent with your unarmed strikes or natural attacks, you deal an extra 1d6 points of bleed damage; this bleed damage does not stack with itself. Once every 1d4 rounds, you can make an unarmed attack with a –5 penalty; if you hit, you deal an additional 2d6 points of bludgeoning damage.",
    "prerequisiteKeys":     [
        "blood frenzy style",
        "improved unarmed strike",
        "power attack"
    ]
}
