{
    "key": "compounded pain",
    "name": "Compounded Pain",
    "url": "https://www.aonprd.com/FeatDisplay.aspx?ItemName=Compounded%20Pain",
    "descriptors": ["Combat"],
    "source": ["Occult Adventures pg. 129"],
    "description": "Your painful stare causes two additional effects.",
    "prerequisites": "Mesmerist level 13th, painful stare class feature.",
    "benefit": "You can apply the effects of two stare feats to your painful stares.",
    "normal": "You can apply the effects of only one stare feat to a given painful stare."
}
