{
    "key": "fiend sight",
    "name": "Fiend Sight",
    "url": "https://www.aonprd.com/FeatDisplay.aspx?ItemName=Fiend%20Sight",
    "source": ["Advanced Race Guide pg. 174"],
    "description": "Your eyes develop keener sight in dim light and darkness.",
    "prerequisites": "Darkvision 60 ft., tiefling",
    "benefit": "You gain low-light vision and your darkvision improves to 120 ft.",
    "special": "You can take this feat twice. When you take it a second time, you gain the see in darkness universal monster ability."
}
