{
    "key": "kitsune vengeance",
    "name": "Kitsune Vengeance",
    "url": "https://www.aonprd.com/FeatDisplay.aspx?ItemName=Kitsune%20Vengeance",
    "descriptors": ["Combat"],
    "source": ["Dirty Tactics Toolbox pg. 15"],
    "description": "You cleverly hide your attacks within your devious antics.",
    "prerequisites": "Int 13; Combat Expertise; Improved Dirty Trick; Kitsune Style; Kitsune Tricks; base attack bonus +6 or monk level 6th.",
    "benefit": "While using the Kitsune Style feat, when a foe provokes an attack of opportunity from you, you can attempt to perform a dirty trick combat maneuver in place of making a melee attack.",
    "prerequisiteKeys":     [
        "combat expertise",
        "improved dirty trick",
        "kitsune style",
        "kitsune tricks"
    ]
}
