{
    "key": "muddled morals",
    "name": "Muddled Morals",
    "url": "https://www.aonprd.com/FeatDisplay.aspx?ItemName=Muddled%20Morals",
    "source": ["Inner Sea Taverns pg. 59"],
    "description": "Your conviction is strong... unless you’ve had a few drinks.",
    "benefit": "You gain a +2 bonus on saving throws against effects that affect you based on your alignment. In addition, choose an alignment one step away from your true alignment; when you are drunk (or worse), spells and other effects affect you as if this alignment were your alignment."
}
