{
    "key": "rat stack",
    "name": "Rat Stack",
    "url": "https://www.aonprd.com/FeatDisplay.aspx?ItemName=Rat%20Stack",
    "descriptors":     [
        "Combat",
        "Teamwork"
    ],
    "source": ["Blood of the Beast pg. 23"],
    "description": "You coordinate efficiently in tight spaces.",
    "prerequisites": "Dex 13, swarming racial trait.",
    "benefit": "You can occupy the same square with up to two other creatures that also have this feat. If all participants also have the Tunnel Rat<sup><sup>ARG<\/sup><\/sup> feat, up to four creatures can share the same space."
}
