{
    "key": "trailblazing channel",
    "name": "Trailblazing Channel",
    "url": "https://www.aonprd.com/FeatDisplay.aspx?ItemName=Trailblazing%20Channel",
    "source": ["Inner Sea Gods pg. 217"],
    "description": "Your positive energy makes trailblazers of those you heal.",
    "prerequisites": "Channel energy 3d6, worshiper of Desna.",
    "benefit": "Once per day when you channel positive energy, you can cause healed creatures to be unimpeded by difficult terrain for a number of minutes equal to your Charisma modifier (minimum 1 minute)."
}
