{
    "key": "bolt of glory",
    "url": "https://www.d20pfsrd.com/magic/all-spells/b/bolt-of-glory/",
    "name": "Bolt of Glory",
    "book": "Copyright 2008, Paizo Publishing, LLC",
    "school": "evocation",
    "descriptors": ["good"],
    "levels": {"glory": 6},
    "castingTime": "1 standard action",
    "components": "V, S, DF",
    "range": "close (25 ft. + 5 ft./level)",
    "target": "ray",
    "duration": "instantaneous",
    "savingThrow": "none",
    "spellResistance": "yes",
    "text": "<p>You fire a ray of positive energy. A creature struck takes varying damage, depending on its nature and home plane of existence.<\/p><ul>  <li>Neutral outsiders and creatures native to the Material Plane and Elemental Planes take 1d6 points of damage per 2 levels (maximum 7d6).<\/li>  <li>Evil outsiders, undead, and natives of the Negative Energy Plane take 1d6 points of damage per level (maximum 15d6).<\/li>  <li>All other creatures take no damage.<\/li> <\/ul>",
    "name_zh": "善良飞矢",
    "castingTime_zh": "标准动作",
    "components_zh": "语言、姿势、法器",
    "effect_zh": "射线",
    "duration_zh": "立即",
    "savingThrow_zh": "无",
    "spellResistance_zh": "可",
    "text_zh": "<p>你射出了一到正能量射线。被击中的生物会受到多种伤害，这取决于它的本质以及生存的母位面。中立的异界生物以及主物质位面和元素位面的本土生物，会受到1d6点/2等级(最多7d6)的伤害。邪恶异界生物、不死生物以及负能量位面的本土生物会受到1d6点/等级(最多15d6)的伤害。其他生物不会受到伤害。<\/p>",
    "source": "CS-PCCS"
}
