{
    "key": "lighten object",
    "url": "https://www.d20pfsrd.com/magic/all-spells/l/lighten-object/",
    "name": "Lighten Object",
    "book": "Pathfinder Campaign Setting: Inner Sea Gods © 2014, Paizo Publishing, LLC",
    "school": "transmutation",
    "levels":     {
        "bard": 1,
        "cleric/oracle": 1,
        "magus": 1,
        "sorcerer/wizard": 1,
        "summoner": 1
    },
    "castingTime": "1 standard action",
    "components": "V, M (goose down)",
    "range": "close (25 ft. + 5 ft./2 levels)",
    "target": "1 object of up to 1 cubic ft./level",
    "duration": "1 min./level",
    "savingThrow": "Will negates (object)",
    "spellResistance": "yes (object)",
    "text": "<p>The target's weight decreases by half. If this spell is cast on armor, the armor's armor check penalty decreases by 1, though its categorization as light, medium, or heavy does not change.<\/p>",
    "name_zh": "轻量化",
    "race_zh": "古拉姆",
    "castingTime_zh": "标准动作",
    "components_zh": "语言，材料（鹅毛）",
    "range_zh": "近距 (25尺+5尺/2等级)",
    "target_zh": "一件一立方英尺的物体/等级",
    "duration_zh": "1分钟/等级",
    "savingThrow_zh": "意志通过则无效（物体）",
    "spellResistance_zh": "可（物体）",
    "text_zh": "<p>这个法术将会减轻目标的重量至原先的一半。如果施放在盔甲上，这将会减轻1点防具检定减值，尽管这不会改变轻、中、重的盔甲类型。<\/p>",
    "source": "CS-ISG"
}
