{
    "key": "lucky number",
    "url": "https://www.d20pfsrd.com/magic/all-spells/l/lucky-number/",
    "name": "Lucky Number",
    "book": "Pathfinder Campaign Setting: Occult Mysteries © 2014, Paizo Inc.",
    "school": "transmutation",
    "levels":     {
        "bard": 1,
        "cleric": 1,
        "druid": 1,
        "inquisitor": 1,
        "paladin": 1,
        "sorcerer/wizard": 1,
        "summoner": 1,
        "witch": 1
    },
    "castingTime": "1 standard action",
    "components": "V, S",
    "range": "touch",
    "target": "one willing creature",
    "duration": "24 hours or until discharged",
    "savingThrow": "none",
    "spellResistance": "no",
    "text": "",
    "name_zh": "幸运数字",
    "castingTime_zh": "标准动作",
    "components_zh": "言语，姿势",
    "range_zh": "接触",
    "target_zh": "一个自愿生物",
    "duration_zh": "24小时或直到发散",
    "savingThrow_zh": "无",
    "spellResistance_zh": "不可",
    "text_zh": "<p>你可以对一个生物短期内的未来施以微调，让它在恰当时机获得好运。投掷一个d20。在法术的持续时间内，只要目标生物掷骰结果为该数字（不论他丢的是多少面骰），这个生物就可以选择重投检定或在该检定结果上获得+2幸运加值。该生物必须在知晓初始掷骰成功与否前选择使用本能力。一个生物同时只能拥有一个幸运数字的法术效果。若一个具有此法术效果的生物再次被施展幸运数字，新的幸运数字法术将取代旧的。<\/p>",
    "source": "CS-OM"
}
