{
    "key": "seeds of influence, greater",
    "url": "https://www.d20pfsrd.com/magic/all-spells/s/seeds-of-influence/",
    "name": "Seeds of Influence, Greater",
    "base": "seeds of influence",
    "book": "Pathfinder Campaign Setting: Inner Sea Intrigue © 2016, Paizo Inc.",
    "school": "enchantment",
    "subSchool": ["compulsion"],
    "descriptors":     [
        "emotion",
        "mind-affecting"
    ],
    "descriptorOperator": "and",
    "levels":     {
        "bard": 5,
        "medium": 4,
        "mesmerist": 5,
        "psychic": 7,
        "sorcerer/wizard": 7,
        "witch": 7
    },
    "duration": "1 day/level (d)",
    "text": "<p>This spell functions as seeds of influence, except that if the target is protected by a spell that grants immunity, spell resistance, or a saving throw bonus against a divination or mind-affecting spell you cast on the target, you can attempt caster level checks to dispel each such effect before applying the effects of those protections against the spell. The DC of the caster level check to dispel each effect is equal to 11 + the effect's caster level. Such spells cast on the target while greater seeds of influence is active grant no protection against greater seeds of influence.<\/p><\/div>",
    "name_zh": "高等影响之种",
    "duration_zh": "1天/等级（可消解）",
    "text_zh": "<p>这种法术类似于影响之种，不过如果目标被施展一个在他面对你的预言术或影响心灵法术时会赋予他免疫、法术抗力、或豁免检定加值的法术时，你可以依次尝试施法者等级检定来消除每一个这样的效果，在它们赋予目标对抗这些法术的保护效果之前。消除每一个效果的施法者等级检定的DC等于11+效果的施法者等级。若对身上已经有激活的高等影响之种的目标施展此类法术，则不会赋予对抗高等影响之种的保护。<\/p>",
    "source": "CS-ISI"
}
